{
  "filters": {
    "byExpr": [
      {
        "name": "62d9d88c42d662ac4cc1",
        "type": "Categorical",
        "filter": {
          "Version": 2,
          "From": [
            {
              "Name": "d",
              "Entity": "dwh Dim_RangoEdad",
              "Type": 0
            }
          ],
          "Where": [
            {
              "Condition": {
                "Not": {
                  "Expression": {
                    "In": {
                      "Expressions": [
                        {
                          "Column": {
                            "Expression": {
                              "SourceRef": {
                                "Source": "d"
                              }
                            },
                            "Property": "RangoEdad"
                          }
                        }
                      ],
                      "Values": [
                        [
                          {
                            "Literal": {
                              "Value": "null"
                            }
                          }
                        ],
                        [
                          {
                            "Literal": {
                              "Value": "'NO DEFINIDO'"
                            }
                          }
                        ]
                      ]
                    }
                  }
                }
              }
            }
          ]
        },
        "expression": {
          "Column": {
            "Expression": {
              "SourceRef": {
                "Entity": "dwh Dim_RangoEdad"
              }
            },
            "Property": "RangoEdad"
          }
        },
        "howCreated": 0
      }
    ]
  },
  "singleVisual": {
    "visualType": "slicer",
    "objects": {
      "merge": {
        "data": [
          {
            "properties": {
              "mode": {
                "expr": {
                  "Literal": {
                    "Value": "'Dropdown'"
                  }
                }
              }
            }
          }
        ],
        "selection": [
          {
            "properties": {
              "strictSingleSelect": {
                "expr": {
                  "Literal": {
                    "Value": "false"
                  }
                }
              }
            }
          }
        ]
      }
    },
    "activeProjections": {
      "Values": [
        {
          "Column": {
            "Expression": {
              "SourceRef": {
                "Entity": "dwh Dim_RangoEdad"
              }
            },
            "Property": "RangoEdad"
          }
        }
      ]
    }
  }
}