{
  "objects": {
    "data": [
      {
        "properties": {
          "mode": {
            "expr": {
              "Literal": {
                "Value": "'Dropdown'"
              }
            }
          }
        }
      }
    ],
    "selection": [
      {
        "properties": {
          "selectAllCheckboxEnabled": {
            "expr": {
              "Literal": {
                "Value": "false"
              }
            }
          },
          "singleSelect": {
            "expr": {
              "Literal": {
                "Value": "false"
              }
            }
          }
        }
      }
    ],
    "general": [
      {
        "properties": {}
      }
    ]
  },
  "projectionOrdering": {
    "Values": [
      0
    ]
  },
  "projectionActiveItems": {
    "Values": [
      {
        "queryRef": "dwh Dim_Afiliado.Distrito",
        "suppressConcat": false
      }
    ]
  },
  "queryMetadata": {
    "Select": [
      {
        "Restatement": "District",
        "Name": "dwh Dim_Afiliado.Distrito",
        "Type": 2048
      }
    ],
    "Filters": [
      {
        "type": 0,
        "expression": {
          "Column": {
            "Expression": {
              "SourceRef": {
                "Entity": "dwh Dim_Afiliado"
              }
            },
            "Property": "Distrito"
          }
        }
      }
    ]
  },
  "visualElements": [
    {
      "DataRoles": [
        {
          "Name": "Values",
          "Projection": 0,
          "isActive": true
        }
      ]
    }
  ],
  "selects": [
    {
      "displayName": "District",
      "queryName": "dwh Dim_Afiliado.Distrito",
      "roles": {
        "Values": true
      },
      "type": {
        "category": null,
        "underlyingType": 1
      },
      "expr": {
        "Column": {
          "Expression": {
            "SourceRef": {
              "Entity": "dwh Dim_Afiliado"
            }
          },
          "Property": "Distrito"
        }
      }
    }
  ]
}